visonic/__init__.py
visonic/alarm.py
visonic/classes.py
visonic/core.py
visonic/devices.py
visonic/exceptions.py
visonicalarm-3.12.0.dist-info/LICENSE
visonicalarm-3.12.0.dist-info/METADATA
visonicalarm-3.12.0.dist-info/WHEEL
visonicalarm-3.12.0.dist-info/top_level.txt
visonicalarm-3.12.0.dist-info/RECORD
