Metadata-Version: 2.1
Name: visonicalarm
Version: 3.12.0
Summary: A simple library for the Visonic Alarm API written in Python 3.
Home-page: https://github.com/bitcanon/visonicalarm
Author: Mikael Schultz
Author-email: bitcanon@pm.me
Classifier: Programming Language :: Python :: 3
Classifier: License :: OSI Approved :: MIT License
Classifier: Operating System :: OS Independent
Requires-Python: >=3.6
License-File: LICENSE
Requires-Dist: requests
Requires-Dist: python-dateutil
